serena/__init__.py
serena/channel.py
serena/connection.py
serena/enums.py
serena/exc.py
serena/frame.py
serena/frameparser.py
serena/message.py
serena/mixin.py
serena/payloads/__init__.py
serena/payloads/encoding.py
serena/payloads/header.py
serena/payloads/method.py
serena/pool.py
serena/py.typed
serena/utils/__init__.py
serena/utils/bitset.py
serena/utils/buffer.py
serena-0.9.1.dist-info/LICENCE
serena-0.9.1.dist-info/LICENCE.GPL
serena-0.9.1.dist-info/METADATA
serena-0.9.1.dist-info/WHEEL
serena-0.9.1.dist-info/RECORD
